dictify/__init__.py
dictify/test.py
dictify-3.2.2.dist-info/LICENSE
dictify-3.2.2.dist-info/METADATA
dictify-3.2.2.dist-info/WHEEL
dictify-3.2.2.dist-info/top_level.txt
dictify-3.2.2.dist-info/RECORD
