Metadata-Version: 2.1
Name: dictify
Version: 3.2.2
Summary: Documents schema and data validation
Home-page: https://nitipit.github.io/dictify/
Author: Nitipit Nontasuwan
Author-email: nitipit@gmail.com
Project-URL: Bug Tracker, https://github.com/nitipit/dictify/issues
Classifier: Programming Language :: Python :: 3
Classifier: License :: OSI Approved :: MIT License
Classifier: Operating System :: OS Independent
Requires-Python: >=3.6
License-File: LICENSE
